cerebro_backtester/__init__.py
cerebro_backtester/backtester_cerebro.py
cerebro_backtester/run.py
cerebro_backtester-10.0.4.dist-info/LICENSE
cerebro_backtester-10.0.4.dist-info/METADATA
cerebro_backtester-10.0.4.dist-info/WHEEL
cerebro_backtester-10.0.4.dist-info/top_level.txt
cerebro_backtester-10.0.4.dist-info/RECORD
