Metadata-Version: 2.1
Name: cerebro_backtester
Version: 10.0.4
Summary: A backtesting framework for evaluating trading strategies on historical market data with features like stop-loss, take-profit, trailing stop, and risk management.
Home-page: https://github.com/nathanschmidt89/cerebro_backtester
Author: Nathan Schmidt
Author-email: Nathan Schmidt <nathan.schmidt.ns89@gmail.com>
Project-URL: Homepage, https://github.com/nathanschmidt89/cerebro_backtester
Project-URL: Issues, https://github.com/nathanschmidt89/cerebro_backtester/issues
Classifier: Programming Language :: Python :: 3
Classifier: License :: OSI Approved :: The Unlicense (Unlicense)
Classifier: Operating System :: OS Independent
Requires-Python: >=3.12
License-File: LICENSE
